senzing_grpc_protobuf/__init__.py
senzing_grpc_protobuf/szconfig_pb2.py
senzing_grpc_protobuf/szconfig_pb2.pyi
senzing_grpc_protobuf/szconfig_pb2_grpc.py
senzing_grpc_protobuf/szconfigmanager_pb2.py
senzing_grpc_protobuf/szconfigmanager_pb2.pyi
senzing_grpc_protobuf/szconfigmanager_pb2_grpc.py
senzing_grpc_protobuf/szdiagnostic_pb2.py
senzing_grpc_protobuf/szdiagnostic_pb2.pyi
senzing_grpc_protobuf/szdiagnostic_pb2_grpc.py
senzing_grpc_protobuf/szengine_pb2.py
senzing_grpc_protobuf/szengine_pb2.pyi
senzing_grpc_protobuf/szengine_pb2_grpc.py
senzing_grpc_protobuf/szproduct_pb2.py
senzing_grpc_protobuf/szproduct_pb2.pyi
senzing_grpc_protobuf/szproduct_pb2_grpc.py
senzing_grpc_protobuf-0.0.3.dist-info/licenses/LICENSE
senzing_grpc_protobuf-0.0.3.dist-info/METADATA
senzing_grpc_protobuf-0.0.3.dist-info/WHEEL
senzing_grpc_protobuf-0.0.3.dist-info/top_level.txt
senzing_grpc_protobuf-0.0.3.dist-info/RECORD
