Metadata-Version: 2.4
Name: senzing_grpc_protobuf
Version: 0.0.3
Summary: auto-generated python protobuf for grpc
Author-email: Senzing <support@senzing.com>
Project-URL: Homepage, https://github.com/senzing-garage/sz-sdk-proto
Project-URL: Bug Tracker, https://github.com/senzing-garage/sz-sdk-proto/issues
Classifier: Programming Language :: Python :: 3
Classifier: License :: OSI Approved :: Apache Software License
Classifier: Operating System :: OS Independent
Requires-Python: >=3.9
License-File: LICENSE
Requires-Dist: protobuf>=6.31.1
Requires-Dist: grpcio>=1.73.1
Dynamic: license-file
